linux_monitoring/__init__.py
linux_monitoring/dao.py
linux_monitoring/data/__init__.py
linux_monitoring/visualization/__init__.py
linux_monitoring-0.0.2.dist-info/LICENCE
linux_monitoring-0.0.2.dist-info/METADATA
linux_monitoring-0.0.2.dist-info/WHEEL
linux_monitoring-0.0.2.dist-info/top_level.txt
linux_monitoring-0.0.2.dist-info/RECORD
